LICENSE
README.md
setup.cfg
setup.py
adafruit_ampy_master.egg-info/PKG-INFO
adafruit_ampy_master.egg-info/SOURCES.txt
adafruit_ampy_master.egg-info/dependency_links.txt
adafruit_ampy_master.egg-info/entry_points.txt
adafruit_ampy_master.egg-info/requires.txt
adafruit_ampy_master.egg-info/top_level.txt
ampy/__init__.py
ampy/cli.py
ampy/files.py
ampy/progress_bar.py
ampy/pyboard.py