Metadata-Version: 2.1
Name: adafruit-ampy-master
Version: 2022.4.22
Summary: Unofficial release of package ampy (Adafruit MicroPython tool), a command line tool to interact with a CircuitPython or MicroPython board over a serial connection.
Home-page: https://github.com/damiencorpataux/ampy
Author: Adafruit Industries
Author-email: d@mien.ch
License: MIT
Keywords: adafruit ampy hardware micropython circuitpython
Platform: UNKNOWN
Classifier: Development Status :: 4 - Beta
Classifier: Intended Audience :: Developers
Classifier: License :: OSI Approved :: MIT License
Classifier: Programming Language :: Python :: 2
Classifier: Programming Language :: Python :: 2.6
Classifier: Programming Language :: Python :: 2.7
Classifier: Programming Language :: Python :: 3
Classifier: Programming Language :: Python :: 3.3
Classifier: Programming Language :: Python :: 3.4
Classifier: Programming Language :: Python :: 3.5
License-File: LICENSE
